{
  "first_part_male": [
    {
      "name": "Веда",
      "description": "Ведающий"
    },
    {
      "name": "Выли",
      "description": "Вышеню любимый"
    },
    {
      "name": "Добро",
      "description": "Добрый"
    },
    {
      "name": "Пердо",
      "description": "Пленящий естеством, райский, дивный"
    },
    {
      "name": "Говна",
      "description": "Господь вышеный"
    },
    {
      "name": "Жида",
      "description": "Жизнь дарящий"
    },
    {
      "name": "Чресло",
      "description": "Гениталиями славящий Оум"
    },
    {
      "name": "Страхо",
      "description": "Сварога-Творца чистый свет хранящий"
    },
    {
      "name": "Пидра",
      "description": "Питающий друзей"
    },
    {
      "name": "Жопо",
      "description": "Жизнь опознающий"
    },
    {
      "name": "Моче",
      "description": "Могущественный и чистый"
    },
    {
      "name": "Дриста",
      "description": "Дариец рода ирийского"
    },
    {
      "name": "Светло",
      "description": "Светом Лады озарённый"
    },
    {
      "name": "Мудо",
      "description": "Мудрый Даждьбога сын"
    },
    {
      "name": "Крыси",
      "description": "Крышеню подобный"
    },
    {
      "name": "Чресла",
      "description": "Гениталии сил лишивший, алчущий"
    },
    {
      "name": "Гавна",
      "description": "Господствующий Аран Воинства Небесного"
    },
    {
      "name": "Жида",
      "description": "Жизни дар в борьбе отстаивающий"
    },
    {
      "name": "Говно",
      "description": "Государь Великого Народа"
    },
    {
      "name": "Дриста",
      "description": "Дружбы истинной алчущий"
    },
    {
      "name": "Дриста",
      "description": "Доблесть рьяно ищущий"
    },
    {
      "name": "Мачу",
      "description": "Макошь чувствующий"
    },
    {
      "name": "Дроче",
      "description": "Д'Арией рода Чернобога"
    },
    {
      "name": "Кароха",
      "description": "Собирающий Карох"
    },
    {
      "name": "Чресла",
      "description": "Гениталиями славящий"
    },
    {
      "name": "Саси",
      "description": "Светоч арийский"
    },
    {
      "name": "Веда",
      "description": "Воспевающий веды, взывающий к ведам"
    },
    {
      "name": "Пени",
      "description": "Перуна восхваляющий"
    },
    {
      "name": "Алка",
      "description": "Алкающий (желающий) любви"
    },
    {
      "name": "Чмыре",
      "description": "Чистый мудрец"
    },
    {
      "name": "Веда",
      "description": "Ведающий высшую духовность славяно-ариев"
    },
    {
      "name": "Перди",
      "description": "Перуна душевный"
    },
    {
      "name": "Яры",
      "description": "яро"
    }
  ],
  "first_part_female": [
    {
      "name": "Веда",
      "description": "Ведающая"
    },
    {
      "name": "Выли",
      "description": "Вышеню любимая"
    },
    {
      "name": "Добро",
      "description": "Добрая"
    },
    {
      "name": "Пердо",
      "description": "Пленящая естеством, райская, дивная"
    },
    {
      "name": "Говна",
      "description": "Господь вышенная"
    },
    {
      "name": "Жида",
      "description": "Жизнь дарящая"
    },
    {
      "name": "Чресло",
      "description": "Гениталиями славящая Оум"
    },
    {
      "name": "Страхо",
      "description": "Сварога-Творца чистый свет хранящая"
    },
    {
      "name": "Пидра",
      "description": "Питающая друзей"
    },
    {
      "name": "Жопо",
      "description": "Жизнь опознающая"
    },
    {
      "name": "Моче",
      "description": "Могущественная и чистая"
    },
    {
      "name": "Дриста",
      "description": "Дарийка рода ирийского"
    },
    {
      "name": "Светло",
      "description": "Светом Лады озарённая"
    },
    {
      "name": "Мудо",
      "description": "Мудрая Даждьбога дочь"
    },
    {
      "name": "Крыси",
      "description": "Крышеню подобная"
    },
    {
      "name": "Чресла",
      "description": "Гениталии сил лишившая, алчущая"
    },
    {
      "name": "Гавна",
      "description": "Господствующая Аран Воинства Небесного"
    },
    {
      "name": "Жида",
      "description": "Жизни дар в борьбе отстаивающая"
    },
    {
      "name": "Говно",
      "description": "Государь Великого Народа"
    },
    {
      "name": "Дриста",
      "description": "Дружбы истинной алчущая"
    },
    {
      "name": "Дриста",
      "description": "Доблесть рьяно ищущая"
    },
    {
      "name": "Мачу",
      "description": "Макошь чувствующая"
    },
    {
      "name": "Дроче",
      "description": "Д'Арией рода Чернобога"
    },
    {
      "name": "Кароха",
      "description": "Собирающая Карох"
    },
    {
      "name": "Чресла",
      "description": "Гениталиями славящая"
    },
    {
      "name": "Саси",
      "description": "Светоч арийская"
    },
    {
      "name": "Веда",
      "description": "Воспевающая веды, взывающий к ведам"
    },
    {
      "name": "Пени",
      "description": "Перуна восхваляющая"
    },
    {
      "name": "Алка",
      "description": "Алкающая (желающая) любви"
    },
    {
      "name": "Чмыре",
      "description": "Чистый мудрец"
    },
    {
      "name": "Веда",
      "description": "Ведающая высшую духовность славяно-ариев"
    },
    {
      "name": "Перди",
      "description": "Перуна душевная"
    },
    {
      "name": "Яры",
      "description": "Яро"
    }
  ],
  "second_part_male": [
    {
      "name": "рас",
      "description": "рассуждающий"
    },
    {
      "name": "зар",
      "description": "знаний арийских алчущий"
    },
    {
      "name": "зар",
      "description": "подобный Заренице"
    },
    {
      "name": "гей",
      "description": "герой"
    },
    {
      "name": "лик",
      "description": "озаряющий ликом"
    },
    {
      "name": "арь",
      "description": "небесный арий"
    },
    {
      "name": "арь",
      "description": "Ариев Рамхи"
    },
    {
      "name": "рмот",
      "description": "ведающий арийскую мудрость"
    },
    {
      "name": "гор",
      "description": "возвышенный"
    },
    {
      "name": "мысл",
      "description": "мыслящий"
    },
    {
      "name": "мысл",
      "description": "стремительный, аки мысль"
    },
    {
      "name": "мысл",
      "description": "мяслями славящий"
    },
    {
      "name": "люд",
      "description": "одаривающий любовью дваждырождённых"
    },
    {
      "name": "слав",
      "description": "славный"
    },
    {
      "name": "слав",
      "description": "Ян славящий"
    },
    {
      "name": "слав",
      "description": "освобождением славные души вознаграждающий"
    },
    {
      "name": "яр",
      "description": "светоч Тарха яростный"
    },
    {
      "name": "яр",
      "description": "яро"
    },
    {
      "name": "зад",
      "description": "юноша Арийский"
    },
    {
      "name": "мудр",
      "description": "мудрный"
    },
    {
      "name": "крод",
      "description": "кродящийся"
    },
    {
      "name": "мор",
      "description": "моногамии отчизнолюб русский"
    },
    {
      "name": "храп",
      "description": "храбрый"
    },
    {
      "name": "бор",
      "description": "борящийся"
    },
    {
      "name": "клюй",
      "description": "окруженный любовью Йога-Майи"
    },
    {
      "name": "врат",
      "description": "вещающий чистый свет Атмы"
    },
    {
      "name": "врат",
      "description": "великий ратник"
    },
    {
      "name": "врат",
      "description": "ведающая Ра творец"
    },
    {
      "name": "пил",
      "description": "пылающий истинной любовью"
    },
    {
      "name": "люб",
      "description": "любящий"
    },
    {
      "name": "мир",
      "description": "силою мистерии истелящий Русь"
    },
    {
      "name": "бол",
      "description": "борящийся любовью"
    },
    {
      "name": "свал",
      "description": "сварожью любящий"
    },
    {
      "name": "бомж",
      "description": "познавший богатство и могущество живы"
    },
    {
      "name": "сил",
      "description": "сильный"
    },
    {
      "name": "сасун",
      "description": "самоотверженный, умный, находчивый"
    },
    {
      "name": "дал",
      "description": "дающий ласку"
    }
  ],
  "second_part_female": [
    {
      "name": "раса",
      "description": "рассуждающая"
    },
    {
      "name": "зара",
      "description": "знаний арийских алчущая"
    },
    {
      "name": "зара",
      "description": "подобная Заренице"
    },
    {
      "name": "гейа",
      "description": "героиня"
    },
    {
      "name": "лика",
      "description": "озаряющая ликом"
    },
    {
      "name": "ария",
      "description": "небесная ария"
    },
    {
      "name": "ария",
      "description": "Ариева Рамхи"
    },
    {
      "name": "рмота",
      "description": "ведающая арийскую мудрость"
    },
    {
      "name": "гора",
      "description": "возвышенная"
    },
    {
      "name": "мысла",
      "description": "мыслящая"
    },
    {
      "name": "мысла",
      "description": "стремительная, аки мысль"
    },
    {
      "name": "мысл",
      "description": "мяслями славящая"
    },
    {
      "name": "люда",
      "description": "дающий ласку"
    },
    {
      "name": "дала",
      "description": "одаривающая любовью дваждырождённых"
    },
    {
      "name": "слава",
      "description": "славная"
    },
    {
      "name": "слава",
      "description": "Ян славящая"
    },
    {
      "name": "слава",
      "description": "освобождением славные души вознаграждающая"
    },
    {
      "name": "яр",
      "description": "яро"
    },
    {
      "name": "яра",
      "description": "светоч Тарха яростная"
    },
    {
      "name": "зада",
      "description": "дева Арийская"
    },
    {
      "name": "мудра",
      "description": "мудрая"
    },
    {
      "name": "крода",
      "description": "кродящаяся"
    },
    {
      "name": "мора",
      "description": "моногамии отчизнолюба русская"
    },
    {
      "name": "храпа",
      "description": "храбрая"
    },
    {
      "name": "бора",
      "description": "борящаяся"
    },
    {
      "name": "клюя",
      "description": "окруженная любовью Йога-Майи"
    },
    {
      "name": "клата",
      "description": "вещающая чистый свет Атмы"
    },
    {
      "name": "врата",
      "description": "великий ратник"
    },
    {
      "name": "пила",
      "description": "пылающая истинной любовью"
    },
    {
      "name": "люба",
      "description": "любящая"
    },
    {
      "name": "мира",
      "description": "силою мистерии истелящая Русь"
    },
    {
      "name": "бола",
      "description": "борящаяся любовью"
    },
    {
      "name": "свала",
      "description": "сварожью любящая"
    },
    {
      "name": "сила",
      "description": "сильная"
    },
    {
      "name": "сасуна",
      "description": "самоотверженная, умная, находчивая"
    },
    {
      "name": "дала",
      "description": "дающая ласку"
    }
  ]
}